{
  "type": "File",
  "start": 0,
  "end": 1202,
  "loc": {
    "start": {
      "line": 1,
      "column": 0
    },
    "end": {
      "line": 42,
      "column": 0
    }
  },
  "program": {
    "type": "Program",
    "start": 0,
    "end": 1202,
    "loc": {
      "start": {
        "line": 1,
        "column": 0
      },
      "end": {
        "line": 42,
        "column": 0
      }
    },
    "sourceType": "module",
    "body": [
      {
        "type": "ImportDeclaration",
        "start": 668,
        "end": 724,
        "loc": {
          "start": {
            "line": 18,
            "column": 0
          },
          "end": {
            "line": 18,
            "column": 56
          }
        },
        "specifiers": [
          {
            "type": "ImportSpecifier",
            "start": 676,
            "end": 690,
            "loc": {
              "start": {
                "line": 18,
                "column": 8
              },
              "end": {
                "line": 18,
                "column": 22
              }
            },
            "imported": {
              "type": "Identifier",
              "start": 676,
              "end": 690,
              "loc": {
                "start": {
                  "line": 18,
                  "column": 8
                },
                "end": {
                  "line": 18,
                  "column": 22
                },
                "identifierName": "ComponentMixin"
              },
              "name": "ComponentMixin",
              "leadingComments": null
            },
            "local": {
              "type": "Identifier",
              "start": 676,
              "end": 690,
              "loc": {
                "start": {
                  "line": 18,
                  "column": 8
                },
                "end": {
                  "line": 18,
                  "column": 22
                },
                "identifierName": "ComponentMixin"
              },
              "name": "ComponentMixin"
            },
            "leadingComments": null
          }
        ],
        "source": {
          "type": "StringLiteral",
          "start": 697,
          "end": 723,
          "loc": {
            "start": {
              "line": 18,
              "column": 29
            },
            "end": {
              "line": 18,
              "column": 55
            }
          },
          "extra": {
            "rawValue": "/coralui-mixin-component",
            "raw": "'/coralui-mixin-component'"
          },
          "value": "/coralui-mixin-component"
        },
        "leadingComments": [
          {
            "type": "CommentBlock",
            "value": "\n * ADOBE CONFIDENTIAL\n *\n * Copyright 2017 Adobe Systems Incorporated\n * All Rights Reserved.\n *\n * NOTICE:  All information contained herein is, and remains\n * the property of Adobe Systems Incorporated and its suppliers,\n * if any.  The intellectual and technical concepts contained\n * herein are proprietary to Adobe Systems Incorporated and its\n * suppliers and may be covered by U.S. and Foreign Patents,\n * patents in process, and are protected by trade secret or copyright law.\n * Dissemination of this information or reproduction of this material\n * is strictly forbidden unless prior written permission is obtained\n * from Adobe Systems Incorporated.\n ",
            "start": 0,
            "end": 666,
            "loc": {
              "start": {
                "line": 1,
                "column": 0
              },
              "end": {
                "line": 16,
                "column": 3
              }
            }
          }
        ]
      },
      {
        "type": "ImportDeclaration",
        "start": 725,
        "end": 775,
        "loc": {
          "start": {
            "line": 19,
            "column": 0
          },
          "end": {
            "line": 19,
            "column": 50
          }
        },
        "specifiers": [
          {
            "type": "ImportSpecifier",
            "start": 733,
            "end": 744,
            "loc": {
              "start": {
                "line": 19,
                "column": 8
              },
              "end": {
                "line": 19,
                "column": 19
              }
            },
            "imported": {
              "type": "Identifier",
              "start": 733,
              "end": 744,
              "loc": {
                "start": {
                  "line": 19,
                  "column": 8
                },
                "end": {
                  "line": 19,
                  "column": 19
                },
                "identifierName": "ButtonMixin"
              },
              "name": "ButtonMixin"
            },
            "local": {
              "type": "Identifier",
              "start": 733,
              "end": 744,
              "loc": {
                "start": {
                  "line": 19,
                  "column": 8
                },
                "end": {
                  "line": 19,
                  "column": 19
                },
                "identifierName": "ButtonMixin"
              },
              "name": "ButtonMixin"
            }
          }
        ],
        "source": {
          "type": "StringLiteral",
          "start": 751,
          "end": 774,
          "loc": {
            "start": {
              "line": 19,
              "column": 26
            },
            "end": {
              "line": 19,
              "column": 49
            }
          },
          "extra": {
            "rawValue": "/coralui-mixin-button",
            "raw": "'/coralui-mixin-button'"
          },
          "value": "/coralui-mixin-button"
        },
        "trailingComments": [
          {
            "type": "CommentBlock",
            "value": "*\n @class Coral.Button\n @classdesc A Button component containing text and/or an icon.\n @htmltag coral-button\n @htmlbasetag button\n @extends {HTMLButtonElement}\n @extends {ComponentMixin}\n @extends {ButtonMixin}\n ",
            "start": 778,
            "end": 994,
            "loc": {
              "start": {
                "line": 22,
                "column": 0
              },
              "end": {
                "line": 30,
                "column": 3
              }
            }
          }
        ]
      },
      {
        "type": "Identifier",
        "start": 995,
        "end": 1177,
        "loc": {
          "start": {
            "line": 31,
            "column": 0
          },
          "end": {
            "line": 39,
            "column": 1
          }
        },
        "id": {
          "type": "Identifier",
          "start": 1001,
          "end": 1007,
          "loc": {
            "start": {
              "line": 31,
              "column": 6
            },
            "end": {
              "line": 31,
              "column": 12
            },
            "identifierName": "Button"
          },
          "name": "Button",
          "leadingComments": null
        },
        "superClass": {
          "type": "CallExpression",
          "start": 1016,
          "end": 1062,
          "loc": {
            "start": {
              "line": 31,
              "column": 21
            },
            "end": {
              "line": 31,
              "column": 67
            }
          },
          "callee": {
            "type": "Identifier",
            "start": 1016,
            "end": 1027,
            "loc": {
              "start": {
                "line": 31,
                "column": 21
              },
              "end": {
                "line": 31,
                "column": 32
              },
              "identifierName": "ButtonMixin"
            },
            "name": "ButtonMixin"
          },
          "arguments": [
            {
              "type": "CallExpression",
              "start": 1028,
              "end": 1061,
              "loc": {
                "start": {
                  "line": 31,
                  "column": 33
                },
                "end": {
                  "line": 31,
                  "column": 66
                }
              },
              "callee": {
                "type": "Identifier",
                "start": 1028,
                "end": 1042,
                "loc": {
                  "start": {
                    "line": 31,
                    "column": 33
                  },
                  "end": {
                    "line": 31,
                    "column": 47
                  },
                  "identifierName": "ComponentMixin"
                },
                "name": "ComponentMixin"
              },
              "arguments": [
                {
                  "type": "Identifier",
                  "start": 1043,
                  "end": 1060,
                  "loc": {
                    "start": {
                      "line": 31,
                      "column": 48
                    },
                    "end": {
                      "line": 31,
                      "column": 65
                    },
                    "identifierName": "HTMLButtonElement"
                  },
                  "name": "HTMLButtonElement"
                }
              ]
            }
          ]
        },
        "body": {
          "type": "ClassBody",
          "start": 1063,
          "end": 1177,
          "loc": {
            "start": {
              "line": 31,
              "column": 68
            },
            "end": {
              "line": 39,
              "column": 1
            }
          },
          "body": [
            {
              "type": "ClassMethod",
              "start": 1084,
              "end": 1175,
              "loc": {
                "start": {
                  "line": 33,
                  "column": 2
                },
                "end": {
                  "line": 38,
                  "column": 3
                }
              },
              "static": false,
              "computed": false,
              "key": {
                "type": "Identifier",
                "start": 1084,
                "end": 1095,
                "loc": {
                  "start": {
                    "line": 33,
                    "column": 2
                  },
                  "end": {
                    "line": 33,
                    "column": 13
                  },
                  "identifierName": "constructor"
                },
                "name": "constructor",
                "leadingComments": null
              },
              "kind": "constructor",
              "id": null,
              "generator": false,
              "expression": false,
              "async": false,
              "params": [],
              "body": {
                "type": "BlockStatement",
                "start": 1098,
                "end": 1175,
                "loc": {
                  "start": {
                    "line": 33,
                    "column": 16
                  },
                  "end": {
                    "line": 38,
                    "column": 3
                  }
                },
                "body": [
                  {
                    "type": "ExpressionStatement",
                    "start": 1104,
                    "end": 1112,
                    "loc": {
                      "start": {
                        "line": 34,
                        "column": 4
                      },
                      "end": {
                        "line": 34,
                        "column": 12
                      }
                    },
                    "expression": {
                      "type": "CallExpression",
                      "start": 1104,
                      "end": 1111,
                      "loc": {
                        "start": {
                          "line": 34,
                          "column": 4
                        },
                        "end": {
                          "line": 34,
                          "column": 11
                        }
                      },
                      "callee": {
                        "type": "Super",
                        "start": 1104,
                        "end": 1109,
                        "loc": {
                          "start": {
                            "line": 34,
                            "column": 4
                          },
                          "end": {
                            "line": 34,
                            "column": 9
                          }
                        }
                      },
                      "arguments": []
                    },
                    "trailingComments": [
                      {
                        "type": "CommentLine",
                        "value": " Events",
                        "start": 1122,
                        "end": 1131,
                        "loc": {
                          "start": {
                            "line": 36,
                            "column": 4
                          },
                          "end": {
                            "line": 36,
                            "column": 13
                          }
                        }
                      }
                    ]
                  },
                  {
                    "type": "ExpressionStatement",
                    "start": 1136,
                    "end": 1171,
                    "loc": {
                      "start": {
                        "line": 37,
                        "column": 4
                      },
                      "end": {
                        "line": 37,
                        "column": 39
                      }
                    },
                    "expression": {
                      "type": "CallExpression",
                      "start": 1136,
                      "end": 1170,
                      "loc": {
                        "start": {
                          "line": 37,
                          "column": 4
                        },
                        "end": {
                          "line": 37,
                          "column": 38
                        }
                      },
                      "callee": {
                        "type": "MemberExpression",
                        "start": 1136,
                        "end": 1156,
                        "loc": {
                          "start": {
                            "line": 37,
                            "column": 4
                          },
                          "end": {
                            "line": 37,
                            "column": 24
                          }
                        },
                        "object": {
                          "type": "ThisExpression",
                          "start": 1136,
                          "end": 1140,
                          "loc": {
                            "start": {
                              "line": 37,
                              "column": 4
                            },
                            "end": {
                              "line": 37,
                              "column": 8
                            }
                          },
                          "leadingComments": null
                        },
                        "property": {
                          "type": "Identifier",
                          "start": 1141,
                          "end": 1156,
                          "loc": {
                            "start": {
                              "line": 37,
                              "column": 9
                            },
                            "end": {
                              "line": 37,
                              "column": 24
                            },
                            "identifierName": "_delegateEvents"
                          },
                          "name": "_delegateEvents"
                        },
                        "computed": false,
                        "leadingComments": null
                      },
                      "arguments": [
                        {
                          "type": "MemberExpression",
                          "start": 1157,
                          "end": 1169,
                          "loc": {
                            "start": {
                              "line": 37,
                              "column": 25
                            },
                            "end": {
                              "line": 37,
                              "column": 37
                            }
                          },
                          "object": {
                            "type": "ThisExpression",
                            "start": 1157,
                            "end": 1161,
                            "loc": {
                              "start": {
                                "line": 37,
                                "column": 25
                              },
                              "end": {
                                "line": 37,
                                "column": 29
                              }
                            }
                          },
                          "property": {
                            "type": "Identifier",
                            "start": 1162,
                            "end": 1169,
                            "loc": {
                              "start": {
                                "line": 37,
                                "column": 30
                              },
                              "end": {
                                "line": 37,
                                "column": 37
                              },
                              "identifierName": "_events"
                            },
                            "name": "_events"
                          },
                          "computed": false
                        }
                      ],
                      "leadingComments": null
                    },
                    "leadingComments": [
                      {
                        "type": "CommentLine",
                        "value": " Events",
                        "start": 1122,
                        "end": 1131,
                        "loc": {
                          "start": {
                            "line": 36,
                            "column": 4
                          },
                          "end": {
                            "line": 36,
                            "column": 13
                          }
                        }
                      }
                    ]
                  }
                ],
                "directives": []
              },
              "leadingComments": [
                {
                  "type": "CommentBlock",
                  "value": "* @ignore ",
                  "start": 1067,
                  "end": 1081,
                  "loc": {
                    "start": {
                      "line": 32,
                      "column": 2
                    },
                    "end": {
                      "line": 32,
                      "column": 16
                    }
                  }
                }
              ]
            }
          ]
        },
        "leadingComments": [],
        "name": "_",
        "trailingComments": []
      },
      {
        "type": "Identifier",
        "start": 1179,
        "end": 1201,
        "loc": {
          "start": {
            "line": 41,
            "column": 0
          },
          "end": {
            "line": 41,
            "column": 22
          }
        },
        "declaration": {
          "type": "Identifier",
          "start": 1194,
          "end": 1200,
          "loc": {
            "start": {
              "line": 41,
              "column": 15
            },
            "end": {
              "line": 41,
              "column": 21
            },
            "identifierName": "Button"
          },
          "name": "Button"
        },
        "name": "_",
        "leadingComments": [],
        "trailingComments": []
      },
      {
        "type": "ExportDefaultDeclaration",
        "start": 1179,
        "end": 1201,
        "loc": {
          "start": {
            "line": 41,
            "column": 0
          },
          "end": {
            "line": 41,
            "column": 22
          }
        },
        "declaration": {
          "type": "ClassDeclaration",
          "start": 995,
          "end": 1177,
          "loc": {
            "start": {
              "line": 31,
              "column": 0
            },
            "end": {
              "line": 39,
              "column": 1
            }
          },
          "id": {
            "type": "Identifier",
            "start": 1001,
            "end": 1007,
            "loc": {
              "start": {
                "line": 31,
                "column": 6
              },
              "end": {
                "line": 31,
                "column": 12
              },
              "identifierName": "Button"
            },
            "name": "Button",
            "leadingComments": null
          },
          "superClass": {
            "type": "CallExpression",
            "start": 1016,
            "end": 1062,
            "loc": {
              "start": {
                "line": 31,
                "column": 21
              },
              "end": {
                "line": 31,
                "column": 67
              }
            },
            "callee": {
              "type": "Identifier",
              "start": 1016,
              "end": 1027,
              "loc": {
                "start": {
                  "line": 31,
                  "column": 21
                },
                "end": {
                  "line": 31,
                  "column": 32
                },
                "identifierName": "ButtonMixin"
              },
              "name": "ButtonMixin"
            },
            "arguments": [
              {
                "type": "CallExpression",
                "start": 1028,
                "end": 1061,
                "loc": {
                  "start": {
                    "line": 31,
                    "column": 33
                  },
                  "end": {
                    "line": 31,
                    "column": 66
                  }
                },
                "callee": {
                  "type": "Identifier",
                  "start": 1028,
                  "end": 1042,
                  "loc": {
                    "start": {
                      "line": 31,
                      "column": 33
                    },
                    "end": {
                      "line": 31,
                      "column": 47
                    },
                    "identifierName": "ComponentMixin"
                  },
                  "name": "ComponentMixin"
                },
                "arguments": [
                  {
                    "type": "Identifier",
                    "start": 1043,
                    "end": 1060,
                    "loc": {
                      "start": {
                        "line": 31,
                        "column": 48
                      },
                      "end": {
                        "line": 31,
                        "column": 65
                      },
                      "identifierName": "HTMLButtonElement"
                    },
                    "name": "HTMLButtonElement"
                  }
                ]
              }
            ]
          },
          "body": {
            "type": "ClassBody",
            "start": 1063,
            "end": 1177,
            "loc": {
              "start": {
                "line": 31,
                "column": 68
              },
              "end": {
                "line": 39,
                "column": 1
              }
            },
            "body": [
              {
                "type": "ClassMethod",
                "start": 1084,
                "end": 1175,
                "loc": {
                  "start": {
                    "line": 33,
                    "column": 2
                  },
                  "end": {
                    "line": 38,
                    "column": 3
                  }
                },
                "static": false,
                "computed": false,
                "key": {
                  "type": "Identifier",
                  "start": 1084,
                  "end": 1095,
                  "loc": {
                    "start": {
                      "line": 33,
                      "column": 2
                    },
                    "end": {
                      "line": 33,
                      "column": 13
                    },
                    "identifierName": "constructor"
                  },
                  "name": "constructor",
                  "leadingComments": null
                },
                "kind": "constructor",
                "id": null,
                "generator": false,
                "expression": false,
                "async": false,
                "params": [],
                "body": {
                  "type": "BlockStatement",
                  "start": 1098,
                  "end": 1175,
                  "loc": {
                    "start": {
                      "line": 33,
                      "column": 16
                    },
                    "end": {
                      "line": 38,
                      "column": 3
                    }
                  },
                  "body": [
                    {
                      "type": "ExpressionStatement",
                      "start": 1104,
                      "end": 1112,
                      "loc": {
                        "start": {
                          "line": 34,
                          "column": 4
                        },
                        "end": {
                          "line": 34,
                          "column": 12
                        }
                      },
                      "expression": {
                        "type": "CallExpression",
                        "start": 1104,
                        "end": 1111,
                        "loc": {
                          "start": {
                            "line": 34,
                            "column": 4
                          },
                          "end": {
                            "line": 34,
                            "column": 11
                          }
                        },
                        "callee": {
                          "type": "Super",
                          "start": 1104,
                          "end": 1109,
                          "loc": {
                            "start": {
                              "line": 34,
                              "column": 4
                            },
                            "end": {
                              "line": 34,
                              "column": 9
                            }
                          }
                        },
                        "arguments": []
                      },
                      "trailingComments": [
                        {
                          "type": "CommentLine",
                          "value": " Events",
                          "start": 1122,
                          "end": 1131,
                          "loc": {
                            "start": {
                              "line": 36,
                              "column": 4
                            },
                            "end": {
                              "line": 36,
                              "column": 13
                            }
                          }
                        }
                      ]
                    },
                    {
                      "type": "ExpressionStatement",
                      "start": 1136,
                      "end": 1171,
                      "loc": {
                        "start": {
                          "line": 37,
                          "column": 4
                        },
                        "end": {
                          "line": 37,
                          "column": 39
                        }
                      },
                      "expression": {
                        "type": "CallExpression",
                        "start": 1136,
                        "end": 1170,
                        "loc": {
                          "start": {
                            "line": 37,
                            "column": 4
                          },
                          "end": {
                            "line": 37,
                            "column": 38
                          }
                        },
                        "callee": {
                          "type": "MemberExpression",
                          "start": 1136,
                          "end": 1156,
                          "loc": {
                            "start": {
                              "line": 37,
                              "column": 4
                            },
                            "end": {
                              "line": 37,
                              "column": 24
                            }
                          },
                          "object": {
                            "type": "ThisExpression",
                            "start": 1136,
                            "end": 1140,
                            "loc": {
                              "start": {
                                "line": 37,
                                "column": 4
                              },
                              "end": {
                                "line": 37,
                                "column": 8
                              }
                            },
                            "leadingComments": null
                          },
                          "property": {
                            "type": "Identifier",
                            "start": 1141,
                            "end": 1156,
                            "loc": {
                              "start": {
                                "line": 37,
                                "column": 9
                              },
                              "end": {
                                "line": 37,
                                "column": 24
                              },
                              "identifierName": "_delegateEvents"
                            },
                            "name": "_delegateEvents"
                          },
                          "computed": false,
                          "leadingComments": null
                        },
                        "arguments": [
                          {
                            "type": "MemberExpression",
                            "start": 1157,
                            "end": 1169,
                            "loc": {
                              "start": {
                                "line": 37,
                                "column": 25
                              },
                              "end": {
                                "line": 37,
                                "column": 37
                              }
                            },
                            "object": {
                              "type": "ThisExpression",
                              "start": 1157,
                              "end": 1161,
                              "loc": {
                                "start": {
                                  "line": 37,
                                  "column": 25
                                },
                                "end": {
                                  "line": 37,
                                  "column": 29
                                }
                              }
                            },
                            "property": {
                              "type": "Identifier",
                              "start": 1162,
                              "end": 1169,
                              "loc": {
                                "start": {
                                  "line": 37,
                                  "column": 30
                                },
                                "end": {
                                  "line": 37,
                                  "column": 37
                                },
                                "identifierName": "_events"
                              },
                              "name": "_events"
                            },
                            "computed": false
                          }
                        ],
                        "leadingComments": null
                      },
                      "leadingComments": [
                        {
                          "type": "CommentLine",
                          "value": " Events",
                          "start": 1122,
                          "end": 1131,
                          "loc": {
                            "start": {
                              "line": 36,
                              "column": 4
                            },
                            "end": {
                              "line": 36,
                              "column": 13
                            }
                          }
                        }
                      ]
                    }
                  ],
                  "directives": []
                },
                "leadingComments": [
                  {
                    "type": "CommentBlock",
                    "value": "* @ignore ",
                    "start": 1067,
                    "end": 1081,
                    "loc": {
                      "start": {
                        "line": 32,
                        "column": 2
                      },
                      "end": {
                        "line": 32,
                        "column": 16
                      }
                    }
                  }
                ]
              }
            ]
          },
          "leadingComments": [
            {
              "type": "CommentBlock",
              "value": "*\n @class Coral.Button\n @classdesc A Button component containing text and/or an icon.\n @htmltag coral-button\n @htmlbasetag button\n @extends {HTMLButtonElement}\n @extends {ComponentMixin}\n @extends {ButtonMixin}\n ",
              "start": 778,
              "end": 994,
              "loc": {
                "start": {
                  "line": 22,
                  "column": 0
                },
                "end": {
                  "line": 30,
                  "column": 3
                }
              }
            }
          ],
          "__PseudoExport__": false,
          "trailingComments": []
        },
        "leadingComments": null
      }
    ],
    "directives": []
  },
  "comments": [
    {
      "type": "CommentBlock",
      "value": "\n * ADOBE CONFIDENTIAL\n *\n * Copyright 2017 Adobe Systems Incorporated\n * All Rights Reserved.\n *\n * NOTICE:  All information contained herein is, and remains\n * the property of Adobe Systems Incorporated and its suppliers,\n * if any.  The intellectual and technical concepts contained\n * herein are proprietary to Adobe Systems Incorporated and its\n * suppliers and may be covered by U.S. and Foreign Patents,\n * patents in process, and are protected by trade secret or copyright law.\n * Dissemination of this information or reproduction of this material\n * is strictly forbidden unless prior written permission is obtained\n * from Adobe Systems Incorporated.\n ",
      "start": 0,
      "end": 666,
      "loc": {
        "start": {
          "line": 1,
          "column": 0
        },
        "end": {
          "line": 16,
          "column": 3
        }
      }
    },
    {
      "type": "CommentBlock",
      "value": "*\n @class Coral.Button\n @classdesc A Button component containing text and/or an icon.\n @htmltag coral-button\n @htmlbasetag button\n @extends {HTMLButtonElement}\n @extends {ComponentMixin}\n @extends {ButtonMixin}\n ",
      "start": 778,
      "end": 994,
      "loc": {
        "start": {
          "line": 22,
          "column": 0
        },
        "end": {
          "line": 30,
          "column": 3
        }
      }
    },
    {
      "type": "CommentBlock",
      "value": "* @ignore ",
      "start": 1067,
      "end": 1081,
      "loc": {
        "start": {
          "line": 32,
          "column": 2
        },
        "end": {
          "line": 32,
          "column": 16
        }
      }
    },
    {
      "type": "CommentLine",
      "value": " Events",
      "start": 1122,
      "end": 1131,
      "loc": {
        "start": {
          "line": 36,
          "column": 4
        },
        "end": {
          "line": 36,
          "column": 13
        }
      }
    }
  ],
  "tokens": [
    {
      "type": "CommentBlock",
      "value": "\n * ADOBE CONFIDENTIAL\n *\n * Copyright 2017 Adobe Systems Incorporated\n * All Rights Reserved.\n *\n * NOTICE:  All information contained herein is, and remains\n * the property of Adobe Systems Incorporated and its suppliers,\n * if any.  The intellectual and technical concepts contained\n * herein are proprietary to Adobe Systems Incorporated and its\n * suppliers and may be covered by U.S. and Foreign Patents,\n * patents in process, and are protected by trade secret or copyright law.\n * Dissemination of this information or reproduction of this material\n * is strictly forbidden unless prior written permission is obtained\n * from Adobe Systems Incorporated.\n ",
      "start": 0,
      "end": 666,
      "loc": {
        "start": {
          "line": 1,
          "column": 0
        },
        "end": {
          "line": 16,
          "column": 3
        }
      }
    },
    {
      "type": {
        "label": "import",
        "keyword": "import",
        "beforeExpr": false,
        "startsExpr": true,
        "rightAssociative": false,
        "isLoop": false,
        "isAssign": false,
        "prefix": false,
        "postfix": false,
        "binop": null,
        "updateContext": null
      },
      "value": "import",
      "start": 668,
      "end": 674,
      "loc": {
        "start": {
          "line": 18,
          "column": 0
        },
        "end": {
          "line": 18,
          "column": 6
        }
      }
    },
    {
      "type": {
        "label": "{",
        "beforeExpr": true,
        "startsExpr": true,
        "rightAssociative": false,
        "isLoop": false,
        "isAssign": false,
        "prefix": false,
        "postfix": false,
        "binop": null
      },
      "start": 675,
      "end": 676,
      "loc": {
        "start": {
          "line": 18,
          "column": 7
        },
        "end": {
          "line": 18,
          "column": 8
        }
      }
    },
    {
      "type": {
        "label": "name",
        "beforeExpr": false,
        "startsExpr": true,
        "rightAssociative": false,
        "isLoop": false,
        "isAssign": false,
        "prefix": false,
        "postfix": false,
        "binop": null
      },
      "value": "ComponentMixin",
      "start": 676,
      "end": 690,
      "loc": {
        "start": {
          "line": 18,
          "column": 8
        },
        "end": {
          "line": 18,
          "column": 22
        }
      }
    },
    {
      "type": {
        "label": "}",
        "beforeExpr": false,
        "startsExpr": false,
        "rightAssociative": false,
        "isLoop": false,
        "isAssign": false,
        "prefix": false,
        "postfix": false,
        "binop": null
      },
      "start": 690,
      "end": 691,
      "loc": {
        "start": {
          "line": 18,
          "column": 22
        },
        "end": {
          "line": 18,
          "column": 23
        }
      }
    },
    {
      "type": {
        "label": "name",
        "beforeExpr": false,
        "startsExpr": true,
        "rightAssociative": false,
        "isLoop": false,
        "isAssign": false,
        "prefix": false,
        "postfix": false,
        "binop": null
      },
      "value": "from",
      "start": 692,
      "end": 696,
      "loc": {
        "start": {
          "line": 18,
          "column": 24
        },
        "end": {
          "line": 18,
          "column": 28
        }
      }
    },
    {
      "type": {
        "label": "string",
        "beforeExpr": false,
        "startsExpr": true,
        "rightAssociative": false,
        "isLoop": false,
        "isAssign": false,
        "prefix": false,
        "postfix": false,
        "binop": null,
        "updateContext": null
      },
      "value": "/coralui-mixin-component",
      "start": 697,
      "end": 723,
      "loc": {
        "start": {
          "line": 18,
          "column": 29
        },
        "end": {
          "line": 18,
          "column": 55
        }
      }
    },
    {
      "type": {
        "label": ";",
        "beforeExpr": true,
        "startsExpr": false,
        "rightAssociative": false,
        "isLoop": false,
        "isAssign": false,
        "prefix": false,
        "postfix": false,
        "binop": null,
        "updateContext": null
      },
      "start": 723,
      "end": 724,
      "loc": {
        "start": {
          "line": 18,
          "column": 55
        },
        "end": {
          "line": 18,
          "column": 56
        }
      }
    },
    {
      "type": {
        "label": "import",
        "keyword": "import",
        "beforeExpr": false,
        "startsExpr": true,
        "rightAssociative": false,
        "isLoop": false,
        "isAssign": false,
        "prefix": false,
        "postfix": false,
        "binop": null,
        "updateContext": null
      },
      "value": "import",
      "start": 725,
      "end": 731,
      "loc": {
        "start": {
          "line": 19,
          "column": 0
        },
        "end": {
          "line": 19,
          "column": 6
        }
      }
    },
    {
      "type": {
        "label": "{",
        "beforeExpr": true,
        "startsExpr": true,
        "rightAssociative": false,
        "isLoop": false,
        "isAssign": false,
        "prefix": false,
        "postfix": false,
        "binop": null
      },
      "start": 732,
      "end": 733,
      "loc": {
        "start": {
          "line": 19,
          "column": 7
        },
        "end": {
          "line": 19,
          "column": 8
        }
      }
    },
    {
      "type": {
        "label": "name",
        "beforeExpr": false,
        "startsExpr": true,
        "rightAssociative": false,
        "isLoop": false,
        "isAssign": false,
        "prefix": false,
        "postfix": false,
        "binop": null
      },
      "value": "ButtonMixin",
      "start": 733,
      "end": 744,
      "loc": {
        "start": {
          "line": 19,
          "column": 8
        },
        "end": {
          "line": 19,
          "column": 19
        }
      }
    },
    {
      "type": {
        "label": "}",
        "beforeExpr": false,
        "startsExpr": false,
        "rightAssociative": false,
        "isLoop": false,
        "isAssign": false,
        "prefix": false,
        "postfix": false,
        "binop": null
      },
      "start": 744,
      "end": 745,
      "loc": {
        "start": {
          "line": 19,
          "column": 19
        },
        "end": {
          "line": 19,
          "column": 20
        }
      }
    },
    {
      "type": {
        "label": "name",
        "beforeExpr": false,
        "startsExpr": true,
        "rightAssociative": false,
        "isLoop": false,
        "isAssign": false,
        "prefix": false,
        "postfix": false,
        "binop": null
      },
      "value": "from",
      "start": 746,
      "end": 750,
      "loc": {
        "start": {
          "line": 19,
          "column": 21
        },
        "end": {
          "line": 19,
          "column": 25
        }
      }
    },
    {
      "type": {
        "label": "string",
        "beforeExpr": false,
        "startsExpr": true,
        "rightAssociative": false,
        "isLoop": false,
        "isAssign": false,
        "prefix": false,
        "postfix": false,
        "binop": null,
        "updateContext": null
      },
      "value": "/coralui-mixin-button",
      "start": 751,
      "end": 774,
      "loc": {
        "start": {
          "line": 19,
          "column": 26
        },
        "end": {
          "line": 19,
          "column": 49
        }
      }
    },
    {
      "type": {
        "label": ";",
        "beforeExpr": true,
        "startsExpr": false,
        "rightAssociative": false,
        "isLoop": false,
        "isAssign": false,
        "prefix": false,
        "postfix": false,
        "binop": null,
        "updateContext": null
      },
      "start": 774,
      "end": 775,
      "loc": {
        "start": {
          "line": 19,
          "column": 49
        },
        "end": {
          "line": 19,
          "column": 50
        }
      }
    },
    {
      "type": "CommentBlock",
      "value": "*\n @class Coral.Button\n @classdesc A Button component containing text and/or an icon.\n @htmltag coral-button\n @htmlbasetag button\n @extends {HTMLButtonElement}\n @extends {ComponentMixin}\n @extends {ButtonMixin}\n ",
      "start": 778,
      "end": 994,
      "loc": {
        "start": {
          "line": 22,
          "column": 0
        },
        "end": {
          "line": 30,
          "column": 3
        }
      }
    },
    {
      "type": {
        "label": "class",
        "keyword": "class",
        "beforeExpr": false,
        "startsExpr": false,
        "rightAssociative": false,
        "isLoop": false,
        "isAssign": false,
        "prefix": false,
        "postfix": false,
        "binop": null,
        "updateContext": null
      },
      "value": "class",
      "start": 995,
      "end": 1000,
      "loc": {
        "start": {
          "line": 31,
          "column": 0
        },
        "end": {
          "line": 31,
          "column": 5
        }
      }
    },
    {
      "type": {
        "label": "name",
        "beforeExpr": false,
        "startsExpr": true,
        "rightAssociative": false,
        "isLoop": false,
        "isAssign": false,
        "prefix": false,
        "postfix": false,
        "binop": null
      },
      "value": "Button",
      "start": 1001,
      "end": 1007,
      "loc": {
        "start": {
          "line": 31,
          "column": 6
        },
        "end": {
          "line": 31,
          "column": 12
        }
      }
    },
    {
      "type": {
        "label": "extends",
        "keyword": "extends",
        "beforeExpr": true,
        "startsExpr": false,
        "rightAssociative": false,
        "isLoop": false,
        "isAssign": false,
        "prefix": false,
        "postfix": false,
        "binop": null,
        "updateContext": null
      },
      "value": "extends",
      "start": 1008,
      "end": 1015,
      "loc": {
        "start": {
          "line": 31,
          "column": 13
        },
        "end": {
          "line": 31,
          "column": 20
        }
      }
    },
    {
      "type": {
        "label": "name",
        "beforeExpr": false,
        "startsExpr": true,
        "rightAssociative": false,
        "isLoop": false,
        "isAssign": false,
        "prefix": false,
        "postfix": false,
        "binop": null
      },
      "value": "ButtonMixin",
      "start": 1016,
      "end": 1027,
      "loc": {
        "start": {
          "line": 31,
          "column": 21
        },
        "end": {
          "line": 31,
          "column": 32
        }
      }
    },
    {
      "type": {
        "label": "(",
        "beforeExpr": true,
        "startsExpr": true,
        "rightAssociative": false,
        "isLoop": false,
        "isAssign": false,
        "prefix": false,
        "postfix": false,
        "binop": null
      },
      "start": 1027,
      "end": 1028,
      "loc": {
        "start": {
          "line": 31,
          "column": 32
        },
        "end": {
          "line": 31,
          "column": 33
        }
      }
    },
    {
      "type": {
        "label": "name",
        "beforeExpr": false,
        "startsExpr": true,
        "rightAssociative": false,
        "isLoop": false,
        "isAssign": false,
        "prefix": false,
        "postfix": false,
        "binop": null
      },
      "value": "ComponentMixin",
      "start": 1028,
      "end": 1042,
      "loc": {
        "start": {
          "line": 31,
          "column": 33
        },
        "end": {
          "line": 31,
          "column": 47
        }
      }
    },
    {
      "type": {
        "label": "(",
        "beforeExpr": true,
        "startsExpr": true,
        "rightAssociative": false,
        "isLoop": false,
        "isAssign": false,
        "prefix": false,
        "postfix": false,
        "binop": null
      },
      "start": 1042,
      "end": 1043,
      "loc": {
        "start": {
          "line": 31,
          "column": 47
        },
        "end": {
          "line": 31,
          "column": 48
        }
      }
    },
    {
      "type": {
        "label": "name",
        "beforeExpr": false,
        "startsExpr": true,
        "rightAssociative": false,
        "isLoop": false,
        "isAssign": false,
        "prefix": false,
        "postfix": false,
        "binop": null
      },
      "value": "HTMLButtonElement",
      "start": 1043,
      "end": 1060,
      "loc": {
        "start": {
          "line": 31,
          "column": 48
        },
        "end": {
          "line": 31,
          "column": 65
        }
      }
    },
    {
      "type": {
        "label": ")",
        "beforeExpr": false,
        "startsExpr": false,
        "rightAssociative": false,
        "isLoop": false,
        "isAssign": false,
        "prefix": false,
        "postfix": false,
        "binop": null
      },
      "start": 1060,
      "end": 1061,
      "loc": {
        "start": {
          "line": 31,
          "column": 65
        },
        "end": {
          "line": 31,
          "column": 66
        }
      }
    },
    {
      "type": {
        "label": ")",
        "beforeExpr": false,
        "startsExpr": false,
        "rightAssociative": false,
        "isLoop": false,
        "isAssign": false,
        "prefix": false,
        "postfix": false,
        "binop": null
      },
      "start": 1061,
      "end": 1062,
      "loc": {
        "start": {
          "line": 31,
          "column": 66
        },
        "end": {
          "line": 31,
          "column": 67
        }
      }
    },
    {
      "type": {
        "label": "{",
        "beforeExpr": true,
        "startsExpr": true,
        "rightAssociative": false,
        "isLoop": false,
        "isAssign": false,
        "prefix": false,
        "postfix": false,
        "binop": null
      },
      "start": 1063,
      "end": 1064,
      "loc": {
        "start": {
          "line": 31,
          "column": 68
        },
        "end": {
          "line": 31,
          "column": 69
        }
      }
    },
    {
      "type": "CommentBlock",
      "value": "* @ignore ",
      "start": 1067,
      "end": 1081,
      "loc": {
        "start": {
          "line": 32,
          "column": 2
        },
        "end": {
          "line": 32,
          "column": 16
        }
      }
    },
    {
      "type": {
        "label": "name",
        "beforeExpr": false,
        "startsExpr": true,
        "rightAssociative": false,
        "isLoop": false,
        "isAssign": false,
        "prefix": false,
        "postfix": false,
        "binop": null
      },
      "value": "constructor",
      "start": 1084,
      "end": 1095,
      "loc": {
        "start": {
          "line": 33,
          "column": 2
        },
        "end": {
          "line": 33,
          "column": 13
        }
      }
    },
    {
      "type": {
        "label": "(",
        "beforeExpr": true,
        "startsExpr": true,
        "rightAssociative": false,
        "isLoop": false,
        "isAssign": false,
        "prefix": false,
        "postfix": false,
        "binop": null
      },
      "start": 1095,
      "end": 1096,
      "loc": {
        "start": {
          "line": 33,
          "column": 13
        },
        "end": {
          "line": 33,
          "column": 14
        }
      }
    },
    {
      "type": {
        "label": ")",
        "beforeExpr": false,
        "startsExpr": false,
        "rightAssociative": false,
        "isLoop": false,
        "isAssign": false,
        "prefix": false,
        "postfix": false,
        "binop": null
      },
      "start": 1096,
      "end": 1097,
      "loc": {
        "start": {
          "line": 33,
          "column": 14
        },
        "end": {
          "line": 33,
          "column": 15
        }
      }
    },
    {
      "type": {
        "label": "{",
        "beforeExpr": true,
        "startsExpr": true,
        "rightAssociative": false,
        "isLoop": false,
        "isAssign": false,
        "prefix": false,
        "postfix": false,
        "binop": null
      },
      "start": 1098,
      "end": 1099,
      "loc": {
        "start": {
          "line": 33,
          "column": 16
        },
        "end": {
          "line": 33,
          "column": 17
        }
      }
    },
    {
      "type": {
        "label": "super",
        "keyword": "super",
        "beforeExpr": false,
        "startsExpr": true,
        "rightAssociative": false,
        "isLoop": false,
        "isAssign": false,
        "prefix": false,
        "postfix": false,
        "binop": null,
        "updateContext": null
      },
      "value": "super",
      "start": 1104,
      "end": 1109,
      "loc": {
        "start": {
          "line": 34,
          "column": 4
        },
        "end": {
          "line": 34,
          "column": 9
        }
      }
    },
    {
      "type": {
        "label": "(",
        "beforeExpr": true,
        "startsExpr": true,
        "rightAssociative": false,
        "isLoop": false,
        "isAssign": false,
        "prefix": false,
        "postfix": false,
        "binop": null
      },
      "start": 1109,
      "end": 1110,
      "loc": {
        "start": {
          "line": 34,
          "column": 9
        },
        "end": {
          "line": 34,
          "column": 10
        }
      }
    },
    {
      "type": {
        "label": ")",
        "beforeExpr": false,
        "startsExpr": false,
        "rightAssociative": false,
        "isLoop": false,
        "isAssign": false,
        "prefix": false,
        "postfix": false,
        "binop": null
      },
      "start": 1110,
      "end": 1111,
      "loc": {
        "start": {
          "line": 34,
          "column": 10
        },
        "end": {
          "line": 34,
          "column": 11
        }
      }
    },
    {
      "type": {
        "label": ";",
        "beforeExpr": true,
        "startsExpr": false,
        "rightAssociative": false,
        "isLoop": false,
        "isAssign": false,
        "prefix": false,
        "postfix": false,
        "binop": null,
        "updateContext": null
      },
      "start": 1111,
      "end": 1112,
      "loc": {
        "start": {
          "line": 34,
          "column": 11
        },
        "end": {
          "line": 34,
          "column": 12
        }
      }
    },
    {
      "type": "CommentLine",
      "value": " Events",
      "start": 1122,
      "end": 1131,
      "loc": {
        "start": {
          "line": 36,
          "column": 4
        },
        "end": {
          "line": 36,
          "column": 13
        }
      }
    },
    {
      "type": {
        "label": "this",
        "keyword": "this",
        "beforeExpr": false,
        "startsExpr": true,
        "rightAssociative": false,
        "isLoop": false,
        "isAssign": false,
        "prefix": false,
        "postfix": false,
        "binop": null,
        "updateContext": null
      },
      "value": "this",
      "start": 1136,
      "end": 1140,
      "loc": {
        "start": {
          "line": 37,
          "column": 4
        },
        "end": {
          "line": 37,
          "column": 8
        }
      }
    },
    {
      "type": {
        "label": ".",
        "beforeExpr": false,
        "startsExpr": false,
        "rightAssociative": false,
        "isLoop": false,
        "isAssign": false,
        "prefix": false,
        "postfix": false,
        "binop": null,
        "updateContext": null
      },
      "start": 1140,
      "end": 1141,
      "loc": {
        "start": {
          "line": 37,
          "column": 8
        },
        "end": {
          "line": 37,
          "column": 9
        }
      }
    },
    {
      "type": {
        "label": "name",
        "beforeExpr": false,
        "startsExpr": true,
        "rightAssociative": false,
        "isLoop": false,
        "isAssign": false,
        "prefix": false,
        "postfix": false,
        "binop": null
      },
      "value": "_delegateEvents",
      "start": 1141,
      "end": 1156,
      "loc": {
        "start": {
          "line": 37,
          "column": 9
        },
        "end": {
          "line": 37,
          "column": 24
        }
      }
    },
    {
      "type": {
        "label": "(",
        "beforeExpr": true,
        "startsExpr": true,
        "rightAssociative": false,
        "isLoop": false,
        "isAssign": false,
        "prefix": false,
        "postfix": false,
        "binop": null
      },
      "start": 1156,
      "end": 1157,
      "loc": {
        "start": {
          "line": 37,
          "column": 24
        },
        "end": {
          "line": 37,
          "column": 25
        }
      }
    },
    {
      "type": {
        "label": "this",
        "keyword": "this",
        "beforeExpr": false,
        "startsExpr": true,
        "rightAssociative": false,
        "isLoop": false,
        "isAssign": false,
        "prefix": false,
        "postfix": false,
        "binop": null,
        "updateContext": null
      },
      "value": "this",
      "start": 1157,
      "end": 1161,
      "loc": {
        "start": {
          "line": 37,
          "column": 25
        },
        "end": {
          "line": 37,
          "column": 29
        }
      }
    },
    {
      "type": {
        "label": ".",
        "beforeExpr": false,
        "startsExpr": false,
        "rightAssociative": false,
        "isLoop": false,
        "isAssign": false,
        "prefix": false,
        "postfix": false,
        "binop": null,
        "updateContext": null
      },
      "start": 1161,
      "end": 1162,
      "loc": {
        "start": {
          "line": 37,
          "column": 29
        },
        "end": {
          "line": 37,
          "column": 30
        }
      }
    },
    {
      "type": {
        "label": "name",
        "beforeExpr": false,
        "startsExpr": true,
        "rightAssociative": false,
        "isLoop": false,
        "isAssign": false,
        "prefix": false,
        "postfix": false,
        "binop": null
      },
      "value": "_events",
      "start": 1162,
      "end": 1169,
      "loc": {
        "start": {
          "line": 37,
          "column": 30
        },
        "end": {
          "line": 37,
          "column": 37
        }
      }
    },
    {
      "type": {
        "label": ")",
        "beforeExpr": false,
        "startsExpr": false,
        "rightAssociative": false,
        "isLoop": false,
        "isAssign": false,
        "prefix": false,
        "postfix": false,
        "binop": null
      },
      "start": 1169,
      "end": 1170,
      "loc": {
        "start": {
          "line": 37,
          "column": 37
        },
        "end": {
          "line": 37,
          "column": 38
        }
      }
    },
    {
      "type": {
        "label": ";",
        "beforeExpr": true,
        "startsExpr": false,
        "rightAssociative": false,
        "isLoop": false,
        "isAssign": false,
        "prefix": false,
        "postfix": false,
        "binop": null,
        "updateContext": null
      },
      "start": 1170,
      "end": 1171,
      "loc": {
        "start": {
          "line": 37,
          "column": 38
        },
        "end": {
          "line": 37,
          "column": 39
        }
      }
    },
    {
      "type": {
        "label": "}",
        "beforeExpr": false,
        "startsExpr": false,
        "rightAssociative": false,
        "isLoop": false,
        "isAssign": false,
        "prefix": false,
        "postfix": false,
        "binop": null
      },
      "start": 1174,
      "end": 1175,
      "loc": {
        "start": {
          "line": 38,
          "column": 2
        },
        "end": {
          "line": 38,
          "column": 3
        }
      }
    },
    {
      "type": {
        "label": "}",
        "beforeExpr": false,
        "startsExpr": false,
        "rightAssociative": false,
        "isLoop": false,
        "isAssign": false,
        "prefix": false,
        "postfix": false,
        "binop": null
      },
      "start": 1176,
      "end": 1177,
      "loc": {
        "start": {
          "line": 39,
          "column": 0
        },
        "end": {
          "line": 39,
          "column": 1
        }
      }
    },
    {
      "type": {
        "label": "export",
        "keyword": "export",
        "beforeExpr": false,
        "startsExpr": false,
        "rightAssociative": false,
        "isLoop": false,
        "isAssign": false,
        "prefix": false,
        "postfix": false,
        "binop": null,
        "updateContext": null
      },
      "value": "export",
      "start": 1179,
      "end": 1185,
      "loc": {
        "start": {
          "line": 41,
          "column": 0
        },
        "end": {
          "line": 41,
          "column": 6
        }
      }
    },
    {
      "type": {
        "label": "default",
        "keyword": "default",
        "beforeExpr": true,
        "startsExpr": false,
        "rightAssociative": false,
        "isLoop": false,
        "isAssign": false,
        "prefix": false,
        "postfix": false,
        "binop": null,
        "updateContext": null
      },
      "value": "default",
      "start": 1186,
      "end": 1193,
      "loc": {
        "start": {
          "line": 41,
          "column": 7
        },
        "end": {
          "line": 41,
          "column": 14
        }
      }
    },
    {
      "type": {
        "label": "name",
        "beforeExpr": false,
        "startsExpr": true,
        "rightAssociative": false,
        "isLoop": false,
        "isAssign": false,
        "prefix": false,
        "postfix": false,
        "binop": null
      },
      "value": "Button",
      "start": 1194,
      "end": 1200,
      "loc": {
        "start": {
          "line": 41,
          "column": 15
        },
        "end": {
          "line": 41,
          "column": 21
        }
      }
    },
    {
      "type": {
        "label": ";",
        "beforeExpr": true,
        "startsExpr": false,
        "rightAssociative": false,
        "isLoop": false,
        "isAssign": false,
        "prefix": false,
        "postfix": false,
        "binop": null,
        "updateContext": null
      },
      "start": 1200,
      "end": 1201,
      "loc": {
        "start": {
          "line": 41,
          "column": 21
        },
        "end": {
          "line": 41,
          "column": 22
        }
      }
    },
    {
      "type": {
        "label": "eof",
        "beforeExpr": false,
        "startsExpr": false,
        "rightAssociative": false,
        "isLoop": false,
        "isAssign": false,
        "prefix": false,
        "postfix": false,
        "binop": null,
        "updateContext": null
      },
      "start": 1202,
      "end": 1202,
      "loc": {
        "start": {
          "line": 42,
          "column": 0
        },
        "end": {
          "line": 42,
          "column": 0
        }
      }
    }
  ]
}